tnetwork/__init__.py
tnetwork/DCD/DCD_metrics.py
tnetwork/DCD/__init__.py
tnetwork/DCD/algorithm_template.py
tnetwork/DCD/benchmarking.py
tnetwork/DCD/benchmarks.py
tnetwork/DCD/communities_scenarios.py
tnetwork/DCD/communities_scenariosSAVE.py
tnetwork/DCD/community.py
tnetwork/DCD/computing_coms_by_sn.py
tnetwork/DCD/multi_temporal_scale.py
tnetwork/DCD/analytics/NMIs.py
tnetwork/DCD/analytics/__init__.py
tnetwork/DCD/analytics/dyn_com_analysis.py
tnetwork/DCD/analytics/dynamic_community.py
tnetwork/DCD/analytics/dynamic_network.py
tnetwork/DCD/analytics/dynamic_partition.py
tnetwork/DCD/analytics/onmi.py
tnetwork/DCD/externals/FacetNetOriginal.py
tnetwork/DCD/externals/Mucha.py
tnetwork/DCD/externals/MuchaLeiden.py
tnetwork/DCD/externals/MuchaOriginal.py
tnetwork/DCD/externals/MuchaOriginal_saved.py
tnetwork/DCD/externals/MuchaReimplemented.py
tnetwork/DCD/externals/PAF.py
tnetwork/DCD/externals/YangOriginal.py
tnetwork/DCD/externals/__init__.py
tnetwork/DCD/externals/command_runner.py
tnetwork/DCD/externals/dynamo.py
tnetwork/DCD/externals/dynmoga.py
tnetwork/DCD/externals/estrangement_confinement.py
tnetwork/DCD/externals/iLCD.py
tnetwork/DCD/externals/utils.py
tnetwork/DCD/externals/GenLouvain-master/__init__.py
tnetwork/DCD/externals/GenLouvain-master/GenLouvain/__init__.py
tnetwork/DCD/externals/GenLouvain-master/GenLouvain/for_redistribution_files_only/__init__.py
tnetwork/DCD/externals/GenLouvain-master/GenLouvain/for_redistribution_files_only/setup.py
tnetwork/DCD/externals/GenLouvain-master/GenLouvain/for_redistribution_files_only/GenLouvain/__init__.py
tnetwork/DCD/externals/GenLouvain-master/GenLouvain/for_testing/__init__.py
tnetwork/DCD/externals/GenLouvain-master/GenLouvain/for_testing/setup.py
tnetwork/DCD/externals/GenLouvain-master/GenLouvain/for_testing/GenLouvain/__init__.py
tnetwork/DCD/externals/RDyn/RDyn.py
tnetwork/DCD/externals/estrangement_master/EstrangementDemo.py
tnetwork/DCD/externals/estrangement_master/__init__.py
tnetwork-1.2.dist-info/LICENSE
tnetwork-1.2.dist-info/METADATA
tnetwork-1.2.dist-info/WHEEL
tnetwork-1.2.dist-info/top_level.txt
tnetwork-1.2.dist-info/RECORD
