Metadata-Version: 2.1
Name: tnetwork
Version: 1.2
Summary: temporal network libary
Home-page: https://github.com/Yquetzal/tnetwork
Author: Remy Cazabet
Author-email: remy.cazabet@gmail.com
License: BSD-Clause-2
Keywords: network-science temporal-networks community-detection
Platform: UNKNOWN
Classifier: Development Status :: 4 - Beta
Classifier: Intended Audience :: Developers
Classifier: Topic :: Software Development :: Build Tools
Classifier: License :: OSI Approved :: BSD License
Classifier: Operating System :: POSIX :: Other
Classifier: Operating System :: MacOS
Classifier: Programming Language :: Python
Classifier: Programming Language :: Python :: 3
Requires-Dist: numpy
Requires-Dist: matplotlib
Requires-Dist: scikit-learn
Requires-Dist: networkx (>=2.4)
Requires-Dist: pandas
Requires-Dist: bokeh
Requires-Dist: progressbar2
Requires-Dist: bidict
Requires-Dist: sphinx-rtd-theme (>=0.3.1)
Requires-Dist: nbsphinx
Requires-Dist: sortedcontainers
